{
    "intents": [
        {
            "tag": "Begruessung",
            "patterns": [
                "Hallo", "Guten Tag", "Servus", "Hey"
            ],
            "responses": [
                "Hallo, ich bin Markus, dein persoenlicher MB-Auswahlassistent!"
            ]
        },
        {
            "tag": "Verabschiedung",
            "patterns": [
                "Danke für die Hilfe", "Tschau", "Tschuess", "Auf Wiedersehen"
            ],
            "responses": [
                "Auf Wiedersehen, bis zum naechsten Mal!", "Danke fuer deinen Besuch!"
            ]
        },
        {
            "tag": "Benzin",
            "patterns": [
                "Benzin", "Benziner", "Benzinmotor", "Ottomotor", "Otto Motor"
            ],
            "responses": [
                "Ein Benziner also...", "Benzin, ist notiert!", "Ich habe 'Benzin' eingeloggt!"
            ]
        },
        {
            "tag": "Hybrid",
            "patterns": [
                "Hybrid", "Elektro und Verbrenner", "PHEV", "Plug In Hybrid", "PlugInHybrid"
            ],
            "responses": [
                "Hybrid ist eingeloggt!", "Habe mir 'Hybrid' notiert.", "Hybrid, habe verstanden."
            ]
        },
        {
            "tag": "Elektrisch",
            "patterns": [
                "Elektrisch", "Elektro", "Stromer", "Klimafreundlich", "E-Motor", "E-Power", "E-Maschine", "Elektroauto"
            ],
            "responses": [
                "Ein Elektroauto also...", "Ich habe 'E-Auto' verstanden!", "Das Elektroauto ist eine gute Wahl!", "E-Auto, ist notiert!"
            ]
        },
        {
            "tag": "Diesel",
            "patterns": [
                "Diesel", "Selbstzünder", "Dieselmotor", "Diesel-Motor"
            ],
            "responses": [
                "Ich logge 'Diesel' ein!", "Diesel, ist notiert!", "Disel, alles klar!", "Diesel, habe ich mir aufgeschrieben!"
            ]
        },
        {
            "tag": "SUV",
            "patterns": [
                "SUV", "Gelände", "geländegänging", "Berge", "hoch sitzen", "bequem einsteigen", "Ja", "SportsUtilityVehicle"
            ],
            "responses": [
                "Ich habe mir 'SUV' aufgeschrieben.", "SUV also. Ich bin auch ein Fan vom hohen Sitzen.", "Welcher SUV darf es denn sein?"
            ]
        },
        {
            "tag": "kein SUV",
            "patterns": [
                "kein SUV", "befestigte Straßen", "Nein"
            ],
            "responses": [
                "Ich habe 'kein SUV' verstanden.", "Ich freue mich, dass du dich fuer die umweltfreundlichere Option entschieden hast!", "'kein SUV' ist eingeloggt!"
            ]
        },
        {
            "tag": "Kompakt",
            "patterns": [
                "A-Klasse", "Klein", "Stadt", "Stadttauglich", "Kompakt", "Kompaktwagen", "sehr kurzer Radstand", "Kompaktklasse", "B-Klasse"
            ],
            "responses": [
                "Ein Kompaktfahrzeug, habe verstanden!", "Der 'Kompaktwagen' ist eingeloggt!", "Kompakt, ist notiert!"
            ]
        },
        {
            "tag": "Mittel",
            "patterns": [
                "C-Klasse", "Mittelklasse", "Mittel", "GLC"
            ],
            "responses": [
                "Ich habe 'Mittelklasse' verstanden.", "Mittelklasse, habe ich mir aufgeschrieben!", "Ich habe 'Mittelklasse' eingeloggt!"
            ]
        },
        {
            "tag": "obere Mittel",
            "patterns": [
                "E-Klasse", "obere Mittelklasse", "obere Mittel", "GLE"
            ],
            "responses": [
                "Obere Mittelklasse, habe verstanden!", "Die 'obere Mittelklasse' ist eingeloggt!", "Ich habe mir 'obere Mittelklasse' aufgeschrieben!", 
                "Ich habe 'obere Mittelklasse verstanden!" 
            ]
        },
        {
            "tag": "Oberklasse",
            "patterns": [
                "S-Klasse", "Oberklasse", "GLS", "teuer"
            ],
            "responses": [
                "Oberklasse, ist notiert!", "Ich habe 'Oberklasse' verstanden", "Ich habe mir 'Oberklasse aufgeschrieben!"
            ]
        },
        {
            "tag": "Luxusklasse",
            "patterns": [
                "Luxusklasse", "Maybach", "das Beste"
            ],
            "responses": [
                "Luxusklasse, ist notiert", "Ich habe mir 'Luxusklasse' aufgeschrieben!", "Die 'Luxusklasse' ist eingeloggt!"
            ]
        },
        {
            "tag": "T-Modell",
            "patterns": [
                "Kombi", "Avant", "Grosser Kofferaum", "praktisch", "T-Modell"
            ],
            "responses": [
                "T-Modell, ist notiert!", "Ein T-Model also...", "T-Modell ist eingeloggt!", "Ich habe mir 'T-Modell' aufgeschrieben!"
            ]
        },
        {
            "tag": "Limousine",
            "patterns": [
                "Limousine", "Edel", "flach"
            ],
            "responses": [
                "Limousine, alles klar!", "Ich habe mir 'Limousine' notiert!", "Die Limousine ist eingeloggt!", "Ich habe 'Limousine' verstanden!"
            ]
        },
        {
            "tag": "Coupe",
            "patterns": [
                "Coupee", "Coupe", "CLA Coupe", "Zweisitzer"
            ],
            "responses": [
                "Ein Coupe also.", "Coupe, ist notiert!", "Ich habe mir 'Coupe' aufgeschrieben!", "Coupe, alles klar!"
            ]
        },
        {
            "tag": "Cabrio",
            "patterns": [
                "Roadster", "Cabrio", "offenes Dach", "kein Dach"
            ],
            "responses": [
                "Ich habe 'Cabrio' verstanden!", "Cabrio, ist notiert!", "Ich habe 'Cabrio' eingeloggt!"
            ]
        },
        {
            "tag": "2Tuerer",
            "patterns": [
                "2 Tueren", "2 Tuerer", "zwei Tueren", "Zweituerer", "CLE", "zwei Türen", "Zweitürer"
            ],
            "responses": [
                "Ich habe 'Zweituerer' verstanden!", "Ich habe 'Zweituerer' eingeloggt", "Zweituerer, ist notiert!"
            ]
        },
        {
            "tag": "4Tuerer",
            "patterns": [
                "4 Türen", "4 Tuerer", "vier Tueren", "Viertuerer", "Vier", "4", "Vier Türen", "Viertürer"
            ],
            "responses": [
                "Viertuerer, habe ich mir aufgescchrieben!", "Viertuerer, ist notiert!", "Ich habe 'Viertuerer eingeloggt!", "Ich habe 'Viertuerer' verstanden!"
            ]
        }
    ]
}